asymongo.py
asymongo-1.3.8.7.dist-info/LICENSE
asymongo-1.3.8.7.dist-info/WHEEL
asymongo-1.3.8.7.dist-info/METADATA
asymongo-1.3.8.7.dist-info/RECORD
