Metadata-Version: 2.1
Name: asymongo
Version: 1.3.8.7
Summary: 异步的 MongoDB ORM
Keywords: asymongo,motor,mongodb,pymongo,orm
Author-email: "lcctoor.com" <lcctoor@outlook.com>
Classifier: License :: OSI Approved :: Apache Software License
Requires-Dist: arts>=2023.11.26
Project-URL: HomePage, https://github.com/lcctoor/arts/tree/main/arts/asymongo
